poligrain/__init__.py
poligrain/example_data.py
poligrain/plot_map.py
poligrain/plot_metadata.py
poligrain/py.typed
poligrain/spatial.py
poligrain/validation.py
poligrain/xarray.py
poligrain-0.3.1.dist-info/LICENSE
poligrain-0.3.1.dist-info/METADATA
poligrain-0.3.1.dist-info/WHEEL
poligrain-0.3.1.dist-info/RECORD
