Metadata-Version: 2.3
Name: poligrain
Version: 0.3.1
Summary: Effortlessly plot and compare (rainfall) sensor data with point, line and grid geometry.
License: BSD-3-Clause
Author: Christian Chwala
Author-email: christian.chwala@kit.edu
Requires-Python: >=3.9,<4.0.0
Classifier: Development Status :: 1 - Planning
Classifier: Intended Audience :: Developers
Classifier: Intended Audience :: Science/Research
Classifier: License :: OSI Approved :: BSD License
Classifier: Operating System :: OS Independent
Classifier: Programming Language :: Python :: 3
Classifier: Programming Language :: Python :: 3.9
Classifier: Programming Language :: Python :: 3.10
Classifier: Programming Language :: Python :: 3.11
Classifier: Programming Language :: Python :: 3.12
Classifier: Programming Language :: Python :: 3.13
Classifier: Topic :: Scientific/Engineering
Classifier: Typing :: Typed
Provides-Extra: dev
Provides-Extra: docs
Provides-Extra: test
Requires-Dist: furo (>=2023.08.17) ; extra == "docs"
Requires-Dist: llvmlite (>=0.42.0)
Requires-Dist: matplotlib (>=3.8.2)
Requires-Dist: myst_parser (>=0.13) ; extra == "docs"
Requires-Dist: nbmake (>=1.4.6) ; extra == "test" or extra == "dev" or extra == "docs"
Requires-Dist: nbsphinx ; extra == "docs"
Requires-Dist: netcdf4 (>=1.6.5)
Requires-Dist: pypandoc-binary ; extra == "docs"
Requires-Dist: pyproj (>=3.6.1)
Requires-Dist: pytest (>=6) ; extra == "test" or extra == "dev"
Requires-Dist: pytest-cov (>=3) ; extra == "test" or extra == "dev"
Requires-Dist: scipy (>=1.12.0)
Requires-Dist: shapely
Requires-Dist: sparse
Requires-Dist: sphinx (>=7.0) ; extra == "docs"
Requires-Dist: sphinx-autodoc-typehints ; extra == "docs"
Requires-Dist: sphinx_copybutton (>=0.3.0) ; extra == "docs"
Requires-Dist: xarray (>=2023.12.0)
Project-URL: Homepage, https://github.com/OpenSenseAction/poligrain
Project-URL: Repository, https://github.com/OpenSenseAction/poligrain
